ChangeLog
LICENSE
MANIFEST.in
README.rst
setup.py
yworklog/__init__.py
yworklog/alembic
yworklog/controller.py
yworklog/core.py
yworklog/fsm.py
yworklog/model.py
yworklog.egg-info/PKG-INFO
yworklog.egg-info/SOURCES.txt
yworklog.egg-info/dependency_links.txt
yworklog.egg-info/entry_points.txt
yworklog.egg-info/requires.txt
yworklog.egg-info/top_level.txt
yworklog/alembic/
yworklog/alembic/alembic.ini
yworklog/alembic/env.py
yworklog/alembic/env.pyc
yworklog/alembic/script.py.mako
yworklog/alembic/versions
yworklog/alembic/versions/2164d7fad520_.py
yworklog/alembic/versions/2164d7fad520_.pyc
yworklog/alembic/versions/3876f3c32a4a_.py
yworklog/alembic/versions/3876f3c32a4a_.pyc
yworklog/git-hooks/prepare-commit-msg