Metadata-Version: 1.0
Name: yworklog
Version: 0.0.7
Summary: YWorkLog
Home-page: https://github.com/yaccz/worklog
Author: Jan Matejka
Author-email: yac@blesmrt.net
License: UNKNOWN
Platform: UNKNOWN
